LICENSE
README.rst
setup.cfg
setup.py
footmark/__init__.py
footmark/connection.py
footmark/exception.py
footmark/provider.py
footmark/regioninfo.py
footmark/resultset.py
footmark.egg-info/PKG-INFO
footmark.egg-info/SOURCES.txt
footmark.egg-info/dependency_links.txt
footmark.egg-info/requires.txt
footmark.egg-info/top_level.txt
footmark/dns/__init__.py
footmark/dns/config.py
footmark/dns/connection.py
footmark/dns/dns.py
footmark/dns/dnsobject.py
footmark/dns/group.py
footmark/dns/regioninfo.py
footmark/ecs/__init__.py
footmark/ecs/config.py
footmark/ecs/connection.py
footmark/ecs/ecsobject.py
footmark/ecs/image.py
footmark/ecs/instance.py
footmark/ecs/instance_type.py
footmark/ecs/keypair.py
footmark/ecs/networkinterface.py
footmark/ecs/regioninfo.py
footmark/ecs/securitygroup.py
footmark/ecs/volume.py
footmark/ecs/vrouter.py
footmark/ecs/zone.py
footmark/ess/__init__.py
footmark/ess/config.py
footmark/ess/configuration.py
footmark/ess/connection.py
footmark/ess/essobject.py
footmark/ess/group.py
footmark/ess/instance.py
footmark/ess/rule.py
footmark/ess/scheduled_task.py
footmark/market/__init__.py
footmark/market/connection.py
footmark/market/product.py
footmark/market/productobject.py
footmark/market/regioninfo.py
footmark/oos/__init__.py
footmark/oos/connection.py
footmark/oos/oos.py
footmark/oos/oosobject.py
footmark/oos/regioninfo.py
footmark/oss/__init__.py
footmark/oss/bucket.py
footmark/oss/connection.py
footmark/oss/regioninfo.py
footmark/oss/test_instance.py
footmark/pyami/__init__.py
footmark/pyami/config.py
footmark/ram/__init__.py
footmark/ram/connection.py
footmark/ram/ram.py
footmark/ram/ramobject.py
footmark/ram/regioninfo.py
footmark/rds/__init__.py
footmark/rds/connection.py
footmark/rds/rds.py
footmark/rds/rdsobject.py
footmark/rds/regioninfo.py
footmark/rds/securitygroup.py
footmark/ros/__init__.py
footmark/ros/connection.py
footmark/slb/__init__.py
footmark/slb/connection.py
footmark/slb/load_balancer.py
footmark/slb/regioninfo.py
footmark/slb/slb.py
footmark/slb/slbobject.py
footmark/slb/vserver_group.py
footmark/sts/__init__.py
footmark/sts/connection.py
footmark/sts/regioninfo.py
